dhm_module_example/__init__.py
dhm_module_example/core.py
dhm_module_example/options.py
dhm_module_example-0.0.1.dist-info/LICENSE
dhm_module_example-0.0.1.dist-info/METADATA
dhm_module_example-0.0.1.dist-info/WHEEL
dhm_module_example-0.0.1.dist-info/entry_points.txt
dhm_module_example-0.0.1.dist-info/top_level.txt
dhm_module_example-0.0.1.dist-info/RECORD
