Metadata-Version: 2.1
Name: dhm-module-example
Version: 0.0.1
Summary: Example that plugs into dhm_module_base
Home-page: https://github.com/Kortforsyningen/dhm-module-example
Author: Nicolai Mogensen
Author-email: nicolai@septima.dk
License: Licensed under the MIT license
Keywords: eksempel
Platform: UNKNOWN
Classifier: Development Status :: 1 - Planning
Classifier: Intended Audience :: Information Technology
Classifier: Intended Audience :: Science/Research
Classifier: Natural Language :: English
Classifier: License :: OSI Approved :: MIT License
Classifier: Programming Language :: Python
Classifier: Programming Language :: Python :: 3
Classifier: Programming Language :: Python :: 3.6
Classifier: Programming Language :: Python :: 3.7
Classifier: Topic :: Scientific/Engineering :: GIS
Requires-Dist: click (>=7.1)
Requires-Dist: click-plugins
Requires-Dist: dhm-module-base (>=0.0.1)
Provides-Extra: dev
Requires-Dist: pytest ; extra == 'dev'
Requires-Dist: black ; extra == 'dev'
